Workbook

Sheet Dashboard
A1: BEYOND TOMORROW FINANCIAL MODEL
A2: Media-led, aligned to the September 2026 deck. The SPV arm is shown at management fees only; carry is long-term upside, not in these numbers. Confidential.
A5: USD | B5: 2026 | C5: 2027 | D5: 2028 | E5: 2029
A6: Total revenue | B6: =PnL!B11 -> 430000 | C6: =PnL!C11 -> 3400000 | D6: =PnL!D11 -> 8000000 | E6: =PnL!E11 -> 22600000
A7: Media | B7: =PnL!B4 -> 300000 | C7: =PnL!C4 -> 1800000 | D7: =PnL!D4 -> 3904000 | E7: =PnL!E4 -> 11580000
A8: EBITDA | B8: =PnL!B21 -> -160000 | C8: =PnL!C21 -> -60000 | D8: =PnL!D21 -> 1510000 | E8: =PnL!E21 -> 9200000
A9: Net profit | B9: =PnL!B24 -> -160000 | C9: =PnL!C24 -> -60000 | D9: =PnL!D24 -> 1208000 | E9: =PnL!E24 -> 7360000
A10: Closing cash | B10: =PnL!B28 -> 1340000 | C10: =PnL!C28 -> 1280000 | D10: =PnL!D28 -> 2488000 | E10: =PnL!E28 -> 9848000
A12: Note
A13: ="Media is the primary driver to "&TEXT(E6/1000000,"$0.0")&"M by 2029. The SPV arm earns management fees only; carry is long-term upside, not in these numbers." -> Media is the primary driver to $22.6M by 2029. The SPV arm earns management fees only; carry is long-term upside, not in these numbers.
A15: Checks
A16: Check | B16: 2026 | C16: 2027 | D16: 2028 | E16: 2029
A17: Total revenue equals media + summits + products + SPV | B17: =IF(ABS(PnL!B11-(PnL!B4+PnL!B5+PnL!B6+PnL!B10))<1,"PASS","FAIL") -> PASS | C17: =IF(ABS(PnL!C11-(PnL!C4+PnL!C5+PnL!C6+PnL!C10))<1,"PASS","FAIL") -> PASS | D17: =IF(ABS(PnL!D11-(PnL!D4+PnL!D5+PnL!D6+PnL!D10))<1,"PASS","FAIL") -> PASS | E17: =IF(ABS(PnL!E11-(PnL!E4+PnL!E5+PnL!E6+PnL!E10))<1,"PASS","FAIL") -> PASS
A18: Closing cash equals opening + raise + net profit | B18: =IF(ABS(PnL!B28-(PnL!B25+PnL!B26+PnL!B27))<1,"PASS","FAIL") -> PASS | C18: =IF(ABS(PnL!C28-(PnL!C25+PnL!C26+PnL!C27))<1,"PASS","FAIL") -> PASS | D18: =IF(ABS(PnL!D28-(PnL!D25+PnL!D26+PnL!D27))<1,"PASS","FAIL") -> PASS | E18: =IF(ABS(PnL!E28-(PnL!E25+PnL!E26+PnL!E27))<1,"PASS","FAIL") -> PASS
A19: Use of funds equals the raise | B19: =IF(ABS(Assumptions!B38-Assumptions!B3)<1,"PASS","FAIL") -> PASS
A20: Use of funds shares sum to 100% | B20: =IF(ABS(Assumptions!C38-1)<0.0001,"PASS","FAIL") -> PASS
A21: Committed does not exceed the raise | B21: =IF(Assumptions!B5<=Assumptions!B3,"PASS","FAIL") -> PASS
A22: Profitability reached in 2028 (2027 EBITDA at or below 0, 2028 above 0) | B22: =IF(AND(PnL!C21<=0,PnL!D21>0),"PASS","FAIL") -> PASS
A23: Any FAIL above means an input no longer ties; check the yellow cells on Assumptions.

Sheet Assumptions
A1: BEYOND TOMORROW ASSUMPTIONS
A2: Edit the yellow cells. Media-led, aligned to the September 2026 deck. The SPV arm earns a management fee on AUM (rate in B7); carry is not modelled and sits as long-term upside.
A3: Raise (USD) | B3: 1500000 | F3: From the deck (slide 15)
A4: Pre-money (USD) | B4: 11000000 | F4: From the deck (slide 15)
A5: Committed (USD) | B5: 660000 | F5: From the deck (slide 15), September 2026. DocSend figures stand, per Julian, 17 Sep 2026
A6: Tax rate | B6: 0.2 | F6: Assumed rate on taxable profit from 2028; confirm with the accountants
A7: SPV mgmt fee rate | B7: 0.008 | F7: Founder input
A8: REVENUE DRIVERS (USD)
A9: Line | B9: 2026 | C9: 2027 | D9: 2028 | E9: 2029 | F9: Basis / confidence
A10: Media: flagship sponsor 1 | B10: 100000 | C10: 520000 | D10: 1304000 | E10: 4000000 | F10: Sponsor ramp built with the founder; aggressive by design, to sign off
A11: Media: flagship sponsor 2 | B11: 80000 | C11: 460000 | D11: 1000000 | E11: 3200000 | F11: Sponsor ramp built with the founder; aggressive by design, to sign off
A12: Media: mid-tier sponsors | B12: 60000 | C12: 350000 | D12: 700000 | E12: 1800000 | F12: Sponsor ramp built with the founder; aggressive by design, to sign off
A13: Media: newsletter & web | B13: 40000 | C13: 250000 | D13: 500000 | E13: 1500000 | F13: Newsletter and web placements on the current audience; aggressive by design, to sign off
A14: Media: AdSense / YouTube | B14: 20000 | C14: 220000 | D14: 400000 | E14: 1080000 | F14: AdSense and YouTube Partner revenue on watch-time growth; aggressive by design, to sign off. 2027 includes the $16k SPV fee moved from 2027 into media, per Julian, 17 Sep 2026
A15: Summits: satellites | B15: 130000 | C15: 500000 | D15: 700000 | E15: 1000000 | F15: Conference-provider JV proposal; 2026 is break-even by design; grounded
A16: Summits: flagship summit | B16: 0 | C16: 1100000 | D16: 2300000 | E16: 7000000 | F16: Conference-provider JV proposal; flagship summit in the US from September 2027; grounded
A17: Products (from 2028) | B17: 0 | C17: 0 | D17: 1000000 | E17: 2700000 | F17: Co-branded longevity products from 2028, about 50% COGS; aggressive in 2029
A18: Investment: SPV AUM (cumulative) | B18: 0 | C18: 0 | D18: 12000000 | E18: 40000000 | F18: Cumulative capital deployed through SPVs; first SPVs deployed in 2028, none in 2027, per Julian, 17 Sep 2026. Pace to sign off
A19: Investment: carry (long-term, not modelled, keep at 0) | B19: 0 | C19: 0 | D19: 0 | E19: 0 | F19: Excluded by design. Carry only crystallises on exits years out
A21: COST DRIVERS (USD)
A22: Line | B22: 2026 | C22: 2027 | D22: 2028 | E22: 2029 | F22: Basis / confidence
A23: Team & salaries | B23: 280000 | C23: 1300000 | D23: 2000000 | E23: 4000000 | F23: Bottom-up construction, scales with revenue; to sign off. 2027 raised by $300k (team funded by the raise, 40% of use of funds) so profitability lands in 2028, per Julian, 17 Sep 2026
A24: Marketing & distribution | B24: 80000 | C24: 750000 | D24: 1500000 | E24: 3800000 | F24: Bottom-up construction, scales with revenue; to sign off
A25: Summit direct costs | B25: 130000 | C25: 850000 | D25: 1600000 | E25: 2400000 | F25: Beyond Tomorrow's share of event costs, from the JV proposal
A26: Content & production | B26: 40000 | C26: 350000 | D26: 400000 | E26: 900000 | F26: Bottom-up construction, scales with revenue; to sign off. 2027 raised by $200k (content funded by the raise, 35% of use of funds) so profitability lands in 2028, per Julian, 17 Sep 2026
A27: Product COGS & fulfilment | B27: 0 | C27: 0 | D27: 500000 | E27: 1350000 | F27: About 50% of product revenue
A28: Investment arm (deal team) | B28: 0 | C28: 60000 | D28: 120000 | E28: 200000 | F28: Deal team from 2027; to sign off
A29: Technology & product | B29: 30000 | C29: 90000 | D29: 250000 | E29: 500000 | F29: Bottom-up construction, scales with revenue; to sign off
A30: Legal, accounting & ops | B30: 30000 | C30: 60000 | D30: 120000 | E30: 250000 | F30: Bottom-up construction, scales with revenue; to sign off
A32: USE OF FUNDS (USD, from the deck, slide 15)
A33: Line | B33: Amount | C33: % of raise | D33: What it funds
A34: Team & operations | B34: 600000 | C34: =B34/$B$3 -> 0.4 | D34: Head of commercial, senior producer, content, ops and finance
A35: Content & distribution | B35: 525000 | C35: =B35/$B$3 -> 0.35 | D35: Studio, video team, paid distribution
A36: Summit execution | B36: 225000 | C36: =B36/$B$3 -> 0.15 | D36: Satellite activations and flagship summit pre-development
A37: Working capital buffer | B37: 150000 | C37: =B37/$B$3 -> 0.1 | D37: Legal, accounting, contingency
A38: Total | B38: =SUM(B34:B37) -> 1500000 | C38: =SUM(C34:C37) -> 1
A39: Check: total equals the raise | B39: =IF(ABS(B38-$B$3)<1,"PASS","FAIL") -> PASS
A41: ROUND STATUS (USD, from the deck, slide 15)
A42: SEIS remaining for UK investors | B42: 20000 | F42: Advance assurance approved; EIS available
A43: Remaining to raise | B43: =B3-B5 -> 840000

Sheet PnL
A1: CONSOLIDATED P&L (calculated)
A3: USD | B3: 2026 | C3: 2027 | D3: 2028 | E3: 2029
A4: Media | B4: =SUM(Assumptions!B10:B14) -> 300000 | C4: =SUM(Assumptions!C10:C14) -> 1800000 | D4: =SUM(Assumptions!D10:D14) -> 3904000 | E4: =SUM(Assumptions!E10:E14) -> 11580000
A5: Summits | B5: =SUM(Assumptions!B15:B16) -> 130000 | C5: =SUM(Assumptions!C15:C16) -> 1600000 | D5: =SUM(Assumptions!D15:D16) -> 3000000 | E5: =SUM(Assumptions!E15:E16) -> 8000000
A6: Products | B6: =Assumptions!B17 -> 0 | C6: =Assumptions!C17 -> 0 | D6: =Assumptions!D17 -> 1000000 | E6: =Assumptions!E17 -> 2700000
A7: Platform revenue | B7: =B4+B5+B6 -> 430000 | C7: =C4+C5+C6 -> 3400000 | D7: =D4+D5+D6 -> 7904000 | E7: =E4+E5+E6 -> 22280000
A8: ="Investment: fees ("&TEXT(Assumptions!$B$7,"0.0%")&" of AUM)" -> Investment: fees (0.8% of AUM) | B8: =Assumptions!B18*Assumptions!$B$7 -> 0 | C8: =Assumptions!C18*Assumptions!$B$7 -> 0 | D8: =Assumptions!D18*Assumptions!$B$7 -> 96000 | E8: =Assumptions!E18*Assumptions!$B$7 -> 320000
A9: Investment: carry | B9: =Assumptions!B19 -> 0 | C9: =Assumptions!C19 -> 0 | D9: =Assumptions!D19 -> 0 | E9: =Assumptions!E19 -> 0
A10: Investment / SPV total | B10: =B8+B9 -> 0 | C10: =C8+C9 -> 0 | D10: =D8+D9 -> 96000 | E10: =E8+E9 -> 320000
A11: Total revenue | B11: =B7+B10 -> 430000 | C11: =C7+C10 -> 3400000 | D11: =D7+D10 -> 8000000 | E11: =E7+E10 -> 22600000
A12: Team & salaries | B12: =Assumptions!B23 -> 280000 | C12: =Assumptions!C23 -> 1300000 | D12: =Assumptions!D23 -> 2000000 | E12: =Assumptions!E23 -> 4000000
A13: Marketing & distribution | B13: =Assumptions!B24 -> 80000 | C13: =Assumptions!C24 -> 750000 | D13: =Assumptions!D24 -> 1500000 | E13: =Assumptions!E24 -> 3800000
A14: Summit direct costs | B14: =Assumptions!B25 -> 130000 | C14: =Assumptions!C25 -> 850000 | D14: =Assumptions!D25 -> 1600000 | E14: =Assumptions!E25 -> 2400000
A15: Content & production | B15: =Assumptions!B26 -> 40000 | C15: =Assumptions!C26 -> 350000 | D15: =Assumptions!D26 -> 400000 | E15: =Assumptions!E26 -> 900000
A16: Product COGS & fulfilment | B16: =Assumptions!B27 -> 0 | C16: =Assumptions!C27 -> 0 | D16: =Assumptions!D27 -> 500000 | E16: =Assumptions!E27 -> 1350000
A17: Investment arm (deal team) | B17: =Assumptions!B28 -> 0 | C17: =Assumptions!C28 -> 60000 | D17: =Assumptions!D28 -> 120000 | E17: =Assumptions!E28 -> 200000
A18: Technology & product | B18: =Assumptions!B29 -> 30000 | C18: =Assumptions!C29 -> 90000 | D18: =Assumptions!D29 -> 250000 | E18: =Assumptions!E29 -> 500000
A19: Legal, accounting & ops | B19: =Assumptions!B30 -> 30000 | C19: =Assumptions!C30 -> 60000 | D19: =Assumptions!D30 -> 120000 | E19: =Assumptions!E30 -> 250000
A20: Total operating costs | B20: =SUM(B12:B19) -> 590000 | C20: =SUM(C12:C19) -> 3460000 | D20: =SUM(D12:D19) -> 6490000 | E20: =SUM(E12:E19) -> 13400000
A21: EBITDA | B21: =B11-B20 -> -160000 | C21: =C11-C20 -> -60000 | D21: =D11-D20 -> 1510000 | E21: =E11-E20 -> 9200000
A22: EBITDA margin | B22: =IFERROR(B21/B11,0) -> -0.37209302 | C22: =IFERROR(C21/C11,0) -> -0.017647059 | D22: =IFERROR(D21/D11,0) -> 0.18875 | E22: =IFERROR(E21/E11,0) -> 0.40707965
A23: Tax | B23: =-MAX(0,B21)*Assumptions!$B$6 -> 0 | C23: =-MAX(0,C21)*Assumptions!$B$6 -> 0 | D23: =-MAX(0,D21)*Assumptions!$B$6 -> -302000 | E23: =-MAX(0,E21)*Assumptions!$B$6 -> -1840000
A24: Net profit / (loss) | B24: =B21+B23 -> -160000 | C24: =C21+C23 -> -60000 | D24: =D21+D23 -> 1208000 | E24: =E21+E23 -> 7360000
A25: Opening cash | B25: 0 | C25: =B28 -> 1340000 | D25: =C28 -> 1280000 | E25: =D28 -> 2488000
A26: + Raise | B26: =Assumptions!$B$3 -> 1500000 | C26: 0 | D26: 0 | E26: 0
A27: + Net profit / (loss) | B27: =B24 -> -160000 | C27: =C24 -> -60000 | D27: =D24 -> 1208000 | E27: =E24 -> 7360000
A28: Closing cash | B28: =B25+B26+B27 -> 1340000 | C28: =C25+C26+C27 -> 1280000 | D28: =D25+D26+D27 -> 2488000 | E28: =E25+E26+E27 -> 9848000
